.DS_Store
cchenutils/__init__.py
cchenutils/__setup__.py
cchenutils/_monitor.py
cchenutils/call.py
cchenutils/dict.py
cchenutils/dictutils.py
cchenutils/driver.py
cchenutils/files.py
cchenutils/gmail.py
cchenutils/hf.py
cchenutils/mp.py
cchenutils/mp_async.py
cchenutils/ntfy.py
cchenutils/pd.py
cchenutils/session.py
cchenutils/timer.py
cchenutils/models/__init__.py
cchenutils/models/classifier.py
cchenutils/text/__init__.py
cchenutils/text/classifier.py
cchenutils/text/classifier_en.py
cchenutils/text/classifier_pclgpt.py
cchenutils/text/classifiers.py
cchenutils/text/preprocessing/__init__.py
cchenutils/text/preprocessing/bertweet.py
cchenutils/text/preprocessing/emojis.py
wanghong/.DS_Store
wanghong/__init__.py
wanghong/async.py
wanghong/dataprep.py
wanghong/opts.py
wanghong/test.py
wanghong/utils.py
wanghong/3rdparty/__init__.py
wanghong/3rdparty/aip/__init__.py
wanghong/3rdparty/aip/base.py
wanghong/3rdparty/aip/face.py
wanghong/3rdparty/aip/imagecensor.py
wanghong/3rdparty/aip/imageclassify.py
wanghong/3rdparty/aip/imagesearch.py
wanghong/3rdparty/aip/kg.py
wanghong/3rdparty/aip/nlp.py
wanghong/3rdparty/aip/ocr.py
wanghong/3rdparty/aip/speech.py
wanghong/3rdparty/pyaudiodata/__init__.py
wanghong/3rdparty/pyaudiodata/recordRadio.py
wanghong/3rdparty/pyaudiodata/testComputational.py
wanghong/prep/__init__.py
wanghong/prep/__process_seq.py
wanghong/prep/_items.py
wanghong/prep/_panel.py
wanghong/prep/_panel_2sellerrate.py
wanghong/prep/_users.py
wanghong/prep/id_map.py
wanghong/prep/mongoexport.py
wanghong/prep/panel_streamother.py
wanghong/prep/taobao_append_rates.py
wanghong/prep/taobao_comments_btm.py
wanghong/prep/taobao_items.py
wanghong/prep/taobao_items_.py
wanghong/prep/taobao_items_category.py
wanghong/prep/taobao_items_embedding.py
wanghong/prep/taobao_items_sku.py
wanghong/prep/taobao_rates.py
wanghong/prep/taobao_rates_.py
wanghong/prep/taobao_rates_dates.py
wanghong/prep/taobao_rates_discounts.py
wanghong/prep/taobao_rates_discounts_agg.py
cchenutils-0.9.26.dist-info/METADATA
cchenutils-0.9.26.dist-info/WHEEL
cchenutils-0.9.26.dist-info/top_level.txt
cchenutils-0.9.26.dist-info/zip-safe
cchenutils-0.9.26.dist-info/RECORD
