Metadata-Version: 2.1
Name: cchenutils
Version: 0.9.26
Summary: cc personal use
Author: chench
Author-email: phantomkidding@gmail.com
License: MIT License
Keywords: utils
Platform: any
Requires-Dist: selenium
Requires-Dist: dask
Requires-Dist: pandas
Requires-Dist: ordered-set
Requires-Dist: schedule
Requires-Dist: nltk
